[{"Latitude":40.7717751,"Longitude":-73.8155812,"geopoint":{"type":"Point","coordinates":[-73.8155812,40.7717751]}},{"Latitude":40.7684554,"Longitude":-73.9044327,"geopoint":{"type":"Point","coordinates":[-73.9044327,40.7684554]}},{"Latitude":40.8270135,"Longitude":-73.8655673,"geopoint":{"type":"Point","coordinates":[-73.8655673,40.8270135]}},{"Latitude":40.6267129,"Longitude":-73.9895684,"geopoint":{"type":"Point","coordinates":[-73.9895684,40.6267129]}},{"Latitude":40.7768249,"Longitude":-73.9888219,"geopoint":{"type":"Point","coordinates":[-73.9888219,40.7768249]}},{"Latitude":40.6391175,"Longitude":-74.0142072,"geopoint":{"type":"Point","coordinates":[-74.0142072,40.6391175]}},{"Latitude":40.742514,"Longitude":-73.8926363,"geopoint":{"type":"Point","coordinates":[-73.8926363,40.742514]}},{"Latitude":40.6760912,"Longitude":-73.7211298,"geopoint":{"type":"Point","coordinates":[-73.7211298,40.6760912]}},{"Latitude":40.6704791,"Longitude":-73.9858725,"geopoint":{"type":"Point","coordinates":[-73.9858725,40.6704791]}},{"Latitude":40.6704523,"Longitude":-73.980636,"geopoint":{"type":"Point","coordinates":[-73.980636,40.6704523]}},{"Latitude":40.725375,"Longitude":-73.843526,"geopoint":{"type":"Point","coordinates":[-73.843526,40.725375]}},{"Latitude":40.8551248,"Longitude":-73.9018591,"geopoint":{"type":"Point","coordinates":[-73.9018591,40.8551248]}},{"Latitude":40.7147169,"Longitude":-73.9958123,"geopoint":{"type":"Point","coordinates":[-73.9958123,40.7147169]}},{"Latitude":40.8342338,"Longitude":-73.8871414,"geopoint":{"type":"Point","coordinates":[-73.8871414,40.8342338]}},{"Latitude":40.7629678,"Longitude":-73.931724,"geopoint":{"type":"Point","coordinates":[-73.931724,40.7629678]}},{"Latitude":40.6807928,"Longitude":-73.9236682,"geopoint":{"type":"Point","coordinates":[-73.9236682,40.6807928]}},{"Latitude":40.7146473,"Longitude":-73.7748547,"geopoint":{"type":"Point","coordinates":[-73.7748547,40.7146473]}},{"Latitude":40.7880607,"Longitude":-73.9508974,"geopoint":{"type":"Point","coordinates":[-73.9508974,40.7880607]}},{"Latitude":40.7407974,"Longitude":-73.8800391,"geopoint":{"type":"Point","coordinates":[-73.8800391,40.7407974]}},{"Latitude":40.6975612,"Longitude":-73.9461875,"geopoint":{"type":"Point","coordinates":[-73.9461875,40.6975612]}}]